{
    "WidgetList": [
		"Nothing",
        "Alteration",
        "Arrow",
        "Arrow (Enchanted)",
		"Axe",
		"Axe (Enchanted)",
		"Battleaxe",
		"Battleaxe (Enchanted)",
		"Bolt",
		"Bolt (Enchanted)",
		"Bow",
		"Bow (Enchanted)",
		"Conjuration",
		"Crossbow",
		"Crossbow (Enchanted)",
		"Dagger",
		"Dagger (Enchanted)",
		"Destruction",
		"Drink",
		"Food",
		"Glove",
		"Greatsword",
		"Greatsword (Enchanted)",
		"Halberd",
		"Illusion",
		"Mace",
		"Mace (Enchanted)",
		"Pike",
		"Pike (Enchanted)",
		"Potion (Blank)",
		"Potion (Health)",
		"Potion (Magicka)",
		"Potion (Poison)",
		"Potion (Stamina)",
		"Power",
		"Restoration",
		"Scroll",
		"Shield",
		"Shield (Enchanted)",
		"Shout",
		"Spellbook",
		"Staff",
		"Sword",
		"Sword (Enchanted)",
		"Torch",
		"Unarmed",
		"Warhammer",
		"Warhammer (Enchanted)"
    ],
    "Path": {
		"Nothing":					"UIHS/NULL.dds",
        "Alteration":				"UIHS/Alteration.dds",
        "Arrow":					"UIHS/Arrow.dds",
        "Arrow (Enchanted)":		"UIHS/ArrowEnchanted.dds",
		"Axe":						"UIHS/Axe.dds",
		"Axe (Enchanted)":			"UIHS/AxeEnchanted.dds",
		"Battleaxe":				"UIHS/Battleaxe.dds",
		"Battleaxe (Enchanted)":	"UIHS/BattleaxeEnchanted.dds",
		"Bolt":						"UIHS/Bolt.dds",
		"Bolt (Enchanted)":			"UIHS/BoltEnchanted.dds",
		"Bow":						"UIHS/Bow.dds",
		"Bow (Enchanted)":			"UIHS/BowEnchanted.dds",
		"Conjuration":				"UIHS/Conjuration.dds",
		"Crossbow":					"UIHS/Crossbow.dds",
		"Crossbow (Enchanted)":		"UIHS/CrossbowEnchanted.dds",
		"Dagger":					"UIHS/Dagger.dds",
		"Dagger (Enchanted)":		"UIHS/DaggerEnchanted.dds",
		"Destruction":				"UIHS/Destruction.dds",
		"Drink":					"UIHS/Drink.dds",
		"Food":						"UIHS/Food.dds",
		"Glove":					"UIHS/Glove.dds",
		"Greatsword":				"UIHS/Greatsword.dds",
		"Greatsword (Enchanted)":	"UIHS/GreatswordEnchanted.dds",
		"Halberd":					"UIHS/Halberd.dds",
		"Illusion":					"UIHS/Illusion.dds",
		"Mace":						"UIHS/Mace.dds",
		"Mace (Enchanted)":			"UIHS/MaceEnchanted.dds",
		"Pike":						"UIHS/Pike.dds",
		"Pike (Enchanted)":			"UIHS/PikeEnchanted.dds",
		"Potion (Blank)":			"UIHS/PotionBlank.dds",
		"Potion (Health)":			"UIHS/PotionHealth.dds",
		"Potion (Magicka)":			"UIHS/PotionMagicka.dds",
		"Potion (Poison)":			"UIHS/PotionPoison.dds",
		"Potion (Stamina)":			"UIHS/PotionStamina.dds",
		"Power":					"UIHS/Power.dds",
		"Restoration":				"UIHS/Restoration.dds",
		"Scroll":					"UIHS/Scroll.dds",
		"Shield":					"UIHS/Shield.dds",
		"Shield (Enchanted)":		"UIHS/ShieldEnchanted.dds",
		"Shout":					"UIHS/Shout.dds",
		"Spellbook":				"UIHS/Spellbook.dds",
		"Staff": 					"UIHS/Staff.dds",
		"Sword":					"UIHS/Sword.dds",
		"Sword (Enchanted)":		"UIHS/SwordEnchanted.dds",
		"Torch":					"UIHS/Torch.dds",
		"Unarmed":					"UIHS/Unarmed.dds",
		"Warhammer":				"UIHS/Warhammer.dds",
		"Warhammer (Enchanted)":	"UIHS/WarhammerEnchanted.dds"
    },
	"Font": [
		"$ConsoleFont",
		"$StartMenuFont",
		"$DialogueFont",
		"$EverywhereFont",
		"$EverywhereBoldFont",
		"$EverywhereMediumFont",
		"$DragonFont",
		"$SkyrimBooks",
		"$HandwrittenFont",
		"$HandwrittenBold",
		"$FalmerFont",
		"$DwemerFont",
		"$DaedricFont",
		"$MageScriptFont",
		"$SkyrimSymbolsFont",
		"$SkyrimBooks_UnreadableFont"
	]
}

